[
	{
		"nome": "Vitor Henrique Rodrigues",
		"idade": 80,
		"cpf": "005.190.918-92",
		"rg": "19.284.226-2",
		"data_nasc": "10/01/1943",
		"sexo": "Masculino",
		"signo": "Capricórnio",
		"mae": "Kamilly Mariana",
		"pai": "Gustavo José Rodrigues",
		"email": "vitorhenriquerodrigues@bb.com.br",
		"senha": "ymEuDZfI30",
		"cep": "69914-378",
		"endereco": "Rua Palmeira",
		"numero": 988,
		"bairro": "Calafate",
		"cidade": "Rio Branco",
		"estado": "AC",
		"telefone_fixo": "(68) 2878-9754",
		"celular": "(68) 99276-8109",
		"altura": "1,98",
		"peso": 56,
		"tipo_sanguineo": "B-",
		"cor": "preto"
	},
	{
		"nome": "Victor Fernando da Costa",
		"idade": 61,
		"cpf": "755.448.259-98",
		"rg": "49.916.120-8",
		"data_nasc": "17/04/1962",
		"sexo": "Masculino",
		"signo": "Áries",
		"mae": "Gabrielly Rayssa",
		"pai": "Anthony Renan Levi da Costa",
		"email": "victor.fernando.dacosta@origamieventos.com.br",
		"senha": "cBQaNqc0oX",
		"cep": "58027-630",
		"endereco": "Rua João Cavalcanti de Albuquerque",
		"numero": 764,
		"bairro": "Mandacaru",
		"cidade": "João Pessoa",
		"estado": "PB",
		"telefone_fixo": "(83) 3795-9226",
		"celular": "(83) 98626-2175",
		"altura": "1,76",
		"peso": 58,
		"tipo_sanguineo": "O-",
		"cor": "vermelho"
	},
	{
		"nome": "Nicolas Anthony Moraes",
		"idade": 46,
		"cpf": "875.361.377-53",
		"rg": "22.115.598-3",
		"data_nasc": "03/02/1977",
		"sexo": "Masculino",
		"signo": "Aquário",
		"mae": "Sabrina Eliane",
		"pai": "Lorenzo Tiago Moraes",
		"email": "nicolasanthonymoraes@akto.com.br",
		"senha": "OLnZ9It4Yt",
		"cep": "70346-110",
		"endereco": "Quadra SQS 107 Bloco K",
		"numero": 490,
		"bairro": "Asa Sul",
		"cidade": "Brasília",
		"estado": "DF",
		"telefone_fixo": "(61) 2828-1751",
		"celular": "(61) 98381-9031",
		"altura": "1,75",
		"peso": 104,
		"tipo_sanguineo": "AB-",
		"cor": "laranja"
	},
	{
		"nome": "Breno José Assunção",
		"idade": 46,
		"cpf": "047.468.981-62",
		"rg": "42.041.989-5",
		"data_nasc": "11/05/1977",
		"sexo": "Masculino",
		"signo": "Touro",
		"mae": "Eliane Márcia",
		"pai": "Ian Fábio Assunção",
		"email": "brenojoseassuncao@termakui.com.br",
		"senha": "8wEeADowCr",
		"cep": "76820-523",
		"endereco": "Rua Mundial",
		"numero": 604,
		"bairro": "Flodoaldo Pontes Pinto",
		"cidade": "Porto Velho",
		"estado": "RO",
		"telefone_fixo": "(69) 2718-4463",
		"celular": "(69) 99375-1340",
		"altura": "1,63",
		"peso": 61,
		"tipo_sanguineo": "B+",
		"cor": "roxo"
	},
	{
		"nome": "Ryan Henrique Almeida",
		"idade": 60,
		"cpf": "217.494.654-85",
		"rg": "25.298.570-9",
		"data_nasc": "01/01/1963",
		"sexo": "Masculino",
		"signo": "Capricórnio",
		"mae": "Luana Sophie Giovanna",
		"pai": "Thiago Rodrigo Bruno Almeida",
		"email": "ryan_almeida@tirantea.com.br",
		"senha": "euo5Wj9iEA",
		"cep": "29048-065",
		"endereco": "Rua da Estiva",
		"numero": 275,
		"bairro": "Joana D'arc",
		"cidade": "Vitória",
		"estado": "ES",
		"telefone_fixo": "(27) 2550-3852",
		"celular": "(27) 99140-5678",
		"altura": "1,69",
		"peso": 98,
		"tipo_sanguineo": "B+",
		"cor": "preto"
	},
	{
		"nome": "Cecília Isabelle Sophia Melo",
		"idade": 26,
		"cpf": "865.203.445-16",
		"rg": "20.382.874-4",
		"data_nasc": "25/03/1997",
		"sexo": "Feminino",
		"signo": "Áries",
		"mae": "Louise Larissa Rosângela",
		"pai": "Enzo Bruno Ian Melo",
		"email": "ceciliaisabellemelo@outlook.com",
		"senha": "dprqxWjQl4",
		"cep": "88350-747",
		"endereco": "Rua Rudi Bononomi",
		"numero": 672,
		"bairro": "Rio Branco",
		"cidade": "Brusque",
		"estado": "SC",
		"telefone_fixo": "(47) 2930-8351",
		"celular": "(47) 98226-5832",
		"altura": "1,72",
		"peso": 89,
		"tipo_sanguineo": "A+",
		"cor": "amarelo"
	},
	{
		"nome": "Liz Marli Duarte",
		"idade": 50,
		"cpf": "783.153.683-38",
		"rg": "39.538.554-4",
		"data_nasc": "01/01/1973",
		"sexo": "Feminino",
		"signo": "Capricórnio",
		"mae": "Bianca Laura Nair",
		"pai": "Filipe Luiz Gabriel Duarte",
		"email": "liz_marli_duarte@flir.com.br",
		"senha": "TKRIyTZPwz",
		"cep": "09520-210",
		"endereco": "Praça Atílio Santarelli",
		"numero": 188,
		"bairro": "Fundação",
		"cidade": "São Caetano do Sul",
		"estado": "SP",
		"telefone_fixo": "(11) 3991-4808",
		"celular": "(11) 99898-4671",
		"altura": "1,77",
		"peso": 75,
		"tipo_sanguineo": "O-",
		"cor": "vermelho"
	},
	{
		"nome": "Yuri Pietro Oliveira",
		"idade": 57,
		"cpf": "969.589.447-04",
		"rg": "28.640.603-2",
		"data_nasc": "12/04/1966",
		"sexo": "Masculino",
		"signo": "Áries",
		"mae": "Raquel Caroline",
		"pai": "Otávio Kauê Mário Oliveira",
		"email": "yuripietrooliveira@terra.com",
		"senha": "ZfpNRWO2TT",
		"cep": "68904-813",
		"endereco": "Avenida Treze de Setembro",
		"numero": 372,
		"bairro": "Novo Buritizal",
		"cidade": "Macapá",
		"estado": "AP",
		"telefone_fixo": "(96) 3885-0352",
		"celular": "(96) 98243-9332",
		"altura": "1,90",
		"peso": 57,
		"tipo_sanguineo": "A-",
		"cor": "preto"
	},
	{
		"nome": "Antonio Renan Peixoto",
		"idade": 25,
		"cpf": "423.963.533-06",
		"rg": "25.952.789-0",
		"data_nasc": "13/04/1998",
		"sexo": "Masculino",
		"signo": "Áries",
		"mae": "Marli Rosa Luana",
		"pai": "Ruan Jorge Pedro Peixoto",
		"email": "antonio.renan.peixoto@unitower.com.br",
		"senha": "Q7pZoszMKi",
		"cep": "72725-209",
		"endereco": "Quadra Quadra 2 Conjunto I",
		"numero": 370,
		"bairro": "Veredas (Brazlândia)",
		"cidade": "Brasília",
		"estado": "DF",
		"telefone_fixo": "(61) 2559-6401",
		"celular": "(61) 99842-5191",
		"altura": "1,85",
		"peso": 87,
		"tipo_sanguineo": "B+",
		"cor": "amarelo"
	},
	{
		"nome": "Lavínia Sônia Beatriz Vieira",
		"idade": 55,
		"cpf": "347.933.425-31",
		"rg": "17.155.585-5",
		"data_nasc": "09/03/1968",
		"sexo": "Feminino",
		"signo": "Peixes",
		"mae": "Márcia Andrea Isabel",
		"pai": "Fábio Ryan Benjamin Vieira",
		"email": "lavinia.sonia.vieira@iq.unesp.br",
		"senha": "NIc2nqwx2W",
		"cep": "81070-330",
		"endereco": "Rua Anilda Moro Ploszaj",
		"numero": 374,
		"bairro": "Portão",
		"cidade": "Curitiba",
		"estado": "PR",
		"telefone_fixo": "(41) 3612-9828",
		"celular": "(41) 99658-7524",
		"altura": "1,73",
		"peso": 51,
		"tipo_sanguineo": "B-",
		"cor": "vermelho"
	},
	{
		"nome": "Lívia Fernanda Emilly Santos",
		"idade": 37,
		"cpf": "385.774.169-41",
		"rg": "15.153.070-1",
		"data_nasc": "20/01/1986",
		"sexo": "Feminino",
		"signo": "Capricórnio",
		"mae": "Débora Natália",
		"pai": "Pietro Anderson Santos",
		"email": "livia.fernanda.santos@consorciogastau.com.br",
		"senha": "PGou990yA6",
		"cep": "72502-201",
		"endereco": "Quadra CL 102 Bloco A",
		"numero": 119,
		"bairro": "Santa Maria",
		"cidade": "Brasília",
		"estado": "DF",
		"telefone_fixo": "(61) 3852-8015",
		"celular": "(61) 99751-1681",
		"altura": "1,69",
		"peso": 75,
		"tipo_sanguineo": "AB+",
		"cor": "roxo"
	},
	{
		"nome": "Agatha Isabelly Rezende",
		"idade": 20,
		"cpf": "735.610.131-98",
		"rg": "41.946.283-1",
		"data_nasc": "19/04/2003",
		"sexo": "Feminino",
		"signo": "Áries",
		"mae": "Marina Rayssa",
		"pai": "André Bernardo Rezende",
		"email": "agathaisabellyrezende@delboux.com.br",
		"senha": "FUYTRqtknU",
		"cep": "24370-283",
		"endereco": "Travessa Antônio Ferreira",
		"numero": 192,
		"bairro": "Jurujuba",
		"cidade": "Niterói",
		"estado": "RJ",
		"telefone_fixo": "(21) 3717-0828",
		"celular": "(21) 99229-2662",
		"altura": "1,52",
		"peso": 45,
		"tipo_sanguineo": "A-",
		"cor": "azul"
	},
	{
		"nome": "Josefa Josefa Figueiredo",
		"idade": 33,
		"cpf": "263.232.500-55",
		"rg": "29.207.571-6",
		"data_nasc": "04/04/1990",
		"sexo": "Feminino",
		"signo": "Áries",
		"mae": "Gabrielly Patrícia Josefa",
		"pai": "Gustavo Igor Carlos Figueiredo",
		"email": "josefa.josefa.figueiredo@ciroconsultoria.com.br",
		"senha": "x0s0FwHxeN",
		"cep": "29312-464",
		"endereco": "Rua Maria da Penha Martins",
		"numero": 334,
		"bairro": "Boa Esperança",
		"cidade": "Cachoeiro de Itapemirim",
		"estado": "ES",
		"telefone_fixo": "(28) 2720-7123",
		"celular": "(28) 98943-8868",
		"altura": "1,70",
		"peso": 57,
		"tipo_sanguineo": "A-",
		"cor": "verde"
	},
	{
		"nome": "Kauê João da Conceição",
		"idade": 77,
		"cpf": "835.755.444-09",
		"rg": "42.789.343-4",
		"data_nasc": "07/01/1946",
		"sexo": "Masculino",
		"signo": "Capricórnio",
		"mae": "Agatha Simone Beatriz",
		"pai": "Cauê César Severino da Conceição",
		"email": "kaue-daconceicao89@bplan.com.br",
		"senha": "mSLN2dxRsz",
		"cep": "64201-185",
		"endereco": "Rua Domingos Lima",
		"numero": 742,
		"bairro": "Santa Isabel",
		"cidade": "Parnaíba",
		"estado": "PI",
		"telefone_fixo": "(86) 3609-6643",
		"celular": "(86) 98437-4702",
		"altura": "1,71",
		"peso": 52,
		"tipo_sanguineo": "B-",
		"cor": "vermelho"
	},
	{
		"nome": "Lívia Marli Lara Silveira",
		"idade": 47,
		"cpf": "982.036.245-88",
		"rg": "23.682.079-5",
		"data_nasc": "26/02/1976",
		"sexo": "Feminino",
		"signo": "Peixes",
		"mae": "Antonella Hadassa Eloá",
		"pai": "Ruan Raul Silveira",
		"email": "livia_silveira@randstad.com.br",
		"senha": "XEEICAifQA",
		"cep": "74786-310",
		"endereco": "Rua Pedro Rosa",
		"numero": 919,
		"bairro": "Residencial Belo Horizonte Complemento",
		"cidade": "Goiânia",
		"estado": "GO",
		"telefone_fixo": "(62) 2799-0450",
		"celular": "(62) 99194-6472",
		"altura": "1,53",
		"peso": 55,
		"tipo_sanguineo": "B-",
		"cor": "vermelho"
	},
	{
		"nome": "Antonio Victor da Cruz",
		"idade": 58,
		"cpf": "817.700.728-96",
		"rg": "18.435.007-4",
		"data_nasc": "15/03/1965",
		"sexo": "Masculino",
		"signo": "Peixes",
		"mae": "Ayla Rosângela",
		"pai": "Igor Carlos da Cruz",
		"email": "antonio.victor.dacruz@mailnull.com",
		"senha": "aDSROuWPcn",
		"cep": "70237-020",
		"endereco": "Quadra SQS 403 Bloco B",
		"numero": 476,
		"bairro": "Asa Sul",
		"cidade": "Brasília",
		"estado": "DF",
		"telefone_fixo": "(61) 2874-8227",
		"celular": "(61) 98131-0727",
		"altura": "1,61",
		"peso": 89,
		"tipo_sanguineo": "AB-",
		"cor": "laranja"
	},
	{
		"nome": "Erick Raimundo da Cunha",
		"idade": 39,
		"cpf": "322.619.984-65",
		"rg": "17.327.705-6",
		"data_nasc": "12/03/1984",
		"sexo": "Masculino",
		"signo": "Peixes",
		"mae": "Nicole Raquel",
		"pai": "Marcos Vinicius Manoel da Cunha",
		"email": "erick_raimundo_dacunha@rubens.adm.br",
		"senha": "c9FTXpAinh",
		"cep": "60440-122",
		"endereco": "Vila Lucivânia",
		"numero": 360,
		"bairro": "Demócrito Rocha",
		"cidade": "Fortaleza",
		"estado": "CE",
		"telefone_fixo": "(85) 3753-8429",
		"celular": "(85) 98813-9421",
		"altura": "1,94",
		"peso": 88,
		"tipo_sanguineo": "AB+",
		"cor": "roxo"
	},
	{
		"nome": "Manuela Marcela Ribeiro",
		"idade": 79,
		"cpf": "078.712.926-76",
		"rg": "27.651.809-3",
		"data_nasc": "10/04/1944",
		"sexo": "Feminino",
		"signo": "Áries",
		"mae": "Mariah Alice Elaine",
		"pai": "Enrico Luan Ribeiro",
		"email": "manuela_marcela_ribeiro@homail.com",
		"senha": "WkkpL5ONww",
		"cep": "35020-100",
		"endereco": "Praça da Catedral",
		"numero": 266,
		"bairro": "Esplanada",
		"cidade": "Governador Valadares",
		"estado": "MG",
		"telefone_fixo": "(33) 2557-4003",
		"celular": "(33) 98327-9522",
		"altura": "1,52",
		"peso": 72,
		"tipo_sanguineo": "B+",
		"cor": "verde"
	},
	{
		"nome": "Alexandre Vicente da Rocha",
		"idade": 33,
		"cpf": "776.423.782-54",
		"rg": "42.764.837-3",
		"data_nasc": "25/02/1990",
		"sexo": "Masculino",
		"signo": "Peixes",
		"mae": "Juliana Jaqueline",
		"pai": "Cláudio Breno da Rocha",
		"email": "alexandre-darocha89@qmagico.com.br",
		"senha": "lYrKgHLlOC",
		"cep": "69060-661",
		"endereco": "Beco Sarapuí",
		"numero": 629,
		"bairro": "Aleixo",
		"cidade": "Manaus",
		"estado": "AM",
		"telefone_fixo": "(92) 2787-7724",
		"celular": "(92) 98288-8257",
		"altura": "1,98",
		"peso": 92,
		"tipo_sanguineo": "A+",
		"cor": "laranja"
	},
	{
		"nome": "Laura Marlene Barros",
		"idade": 66,
		"cpf": "618.567.765-22",
		"rg": "28.406.960-7",
		"data_nasc": "27/03/1957",
		"sexo": "Feminino",
		"signo": "Áries",
		"mae": "Sônia Alana Luciana",
		"pai": "Danilo Thomas Barros",
		"email": "laura_marlene_barros@terra.com.br",
		"senha": "u1MmrpxYeo",
		"cep": "57300-800",
		"endereco": "Rua Maurício Pereira",
		"numero": 349,
		"bairro": "Centro",
		"cidade": "Arapiraca",
		"estado": "AL",
		"telefone_fixo": "(82) 3732-3068",
		"celular": "(82) 99101-1365",
		"altura": "1,59",
		"peso": 58,
		"tipo_sanguineo": "AB+",
		"cor": "vermelho"
	}
]